{
  "add": { "latex": "{v1} + {v2}", "type": "infix", "sec": "arithmetic" },
  "sub": { "latex": "{v1} - {v2}", "type": "infix", "sec": "arithmetic" },
  "pm": { "latex": "{v1} \\pm {v2}", "type": "infix", "sec": "arithmetic" },
  "mul_cross": { "latex": "{v1} \\times {v2}", "type": "infix", "sec": "arithmetic" },
  "mul_dot": { "latex": "{v1} \\cdot {v2}", "type": "infix", "sec": "arithmetic" },
  "div": { "latex": "{v1} \\div {v2}", "type": "infix", "sec": "arithmetic" },
  "slash_div": { "latex": "{v1}/{v2}", "type": "infix", "sec": "arithmetic" },
  "eq": { "latex": "{v1} = {v2}", "type": "infix", "sec": "arithmetic" },
  "neq": { "latex": "{v1} \\neq {v2}", "type": "infix", "sec": "arithmetic" },
  "lt": { "latex": "{v1} < {v2}", "type": "infix", "sec": "arithmetic" },
  "gt": { "latex": "{v1} > {v2}", "type": "infix", "sec": "arithmetic" },
  "le": { "latex": "{v1} \\le {v2}", "type": "infix", "sec": "arithmetic" },
  "ge": { "latex": "{v1} \\ge {v2}", "type": "infix", "sec": "arithmetic" },
  "approx": { "latex": "{v1} \\approx {v2}", "type": "infix", "sec": "arithmetic" },
  "sim": { "latex": "{v1} \\sim {v2}", "type": "infix", "sec": "arithmetic" },
  "pow": { "latex": "{v1}^{{{v2}}}", "type": "infix", "sec": "arithmetic" },
  "sqrt": { "latex": "\\sqrt{{{v1}}}", "type": "prefix", "sec": "arithmetic" },
  "sqrt_n": { "latex": "\\sqrt[{v2}]{{{v1}}}", "type": "prefix", "sec": "arithmetic" },
  "abs": { "latex": "|{v1}|", "type": "prefix", "sec": "arithmetic" },
  "factorial": { "latex": "{v1}!", "type": "suffix", "sec": "arithmetic" },

  "deriv_lagrange": { "latex": "{v1}'", "type": "suffix", "sec": "calculus" },
  "deriv_leibniz": { "latex": "\\frac{{d{v1}}}{{d{v2}}}", "type": "functional", "sec": "calculus" },
  "deriv_partial": { "latex": "\\frac{{\\partial {v1}}}{{\\partial {v2}}}", "type": "functional", "sec": "calculus" },
  "deriv_dot": { "latex": "\\dot{{{v1}}}", "type": "prefix", "sec": "calculus" },
  "grad": { "latex": "\\nabla {v1}", "type": "prefix", "sec": "calculus" },
  "laplacian": { "latex": "\\Delta {v1}", "type": "prefix", "sec": "calculus" },
  "dalembertian": { "latex": "\\square {v1}", "type": "prefix", "sec": "calculus" },
  "composition": { "latex": "({v1} \\circ {v2})", "type": "infix", "sec": "calculus" },
  "convolution": { "latex": "({v1} \\ast {v2})", "type": "infix", "sec": "calculus" },
  "limit": { "latex": "\\lim_{{{v2} \\to a}} {v1}", "type": "functional", "sec": "calculus" },
  "limsup": { "latex": "\\limsup_{{{v2} \\to a}} {v1}", "type": "functional", "sec": "calculus" },
  "liminf": { "latex": "\\liminf_{{{v2} \\to a}} {v1}", "type": "functional", "sec": "calculus" },
  "integral_def": { "latex": "\\int_{{a}}^{{b}} {v1} d{v2}", "type": "functional", "sec": "calculus" },
  "integral_contour": { "latex": "\\oint {v1} d{v2}", "type": "functional", "sec": "calculus" },
  "integral_double": { "latex": "\\iint {v1} dA", "type": "prefix", "sec": "calculus" },
  "integral_triple": { "latex": "\\iiint {v1} dV", "type": "prefix", "sec": "calculus" },
  "integral_indef": { "latex": "\\int {v1} d{v2}", "type": "functional", "sec": "calculus" },
  "sum_finite": { "latex": "\\sum_{{i=1}}^{{n}} {v1}_i", "type": "prefix", "sec": "calculus" },
  "sum_inf": { "latex": "\\sum_{{i=0}}^{{\\infty}} {v1}_i", "type": "prefix", "sec": "calculus" },
  "prod_finite": { "latex": "\\prod_{{i=1}}^{{n}} {v1}_i", "type": "prefix", "sec": "calculus" },
  "coprod": { "latex": "\\coprod {v1}", "type": "prefix", "sec": "calculus" },

  "membership": { "latex": "{v1} \\in {v2}", "type": "infix", "sec": "sets" },
  "not_membership": { "latex": "{v1} \\notin {v2}", "type": "infix", "sec": "sets" },
  "subset_strict": { "latex": "{v1} \\subset {v2}", "type": "infix", "sec": "sets" },
  "subset_eq": { "latex": "{v1} \\subseteq {v2}", "type": "infix", "sec": "sets" },
  "superset_strict": { "latex": "{v1} \\supset {v2}", "type": "infix", "sec": "sets" },
  "superset_eq": { "latex": "{v1} \\supseteq {v2}", "type": "infix", "sec": "sets" },
  "union": { "latex": "{v1} \\cup {v2}", "type": "infix", "sec": "sets" },
  "intersect": { "latex": "{v1} \\cap {v2}", "type": "infix", "sec": "sets" },
  "setminus": { "latex": "{v1} \\setminus {v2}", "type": "infix", "sec": "sets" },
  "sym_diff": { "latex": "{v1} \\triangle {v2}", "type": "infix", "sec": "sets" },
  "cartesian": { "latex": "{v1} \\times {v2}", "type": "infix", "sec": "sets" },
  "powerset": { "latex": "\\mathcal{{P}}({v1})", "type": "prefix", "sec": "sets" },
  "cardinality": { "latex": "|{v1}|", "type": "prefix", "sec": "sets" },

  "dot_prod_vec": { "latex": "{v1} \\cdot {v2}", "type": "infix", "sec": "linalg" },
  "cross_prod_vec": { "latex": "{v1} \\times {v2}", "type": "infix", "sec": "linalg" },
  "tensor_prod": { "latex": "{v1} \\otimes {v2}", "type": "infix", "sec": "linalg" },
  "direct_sum": { "latex": "{v1} \\oplus {v2}", "type": "infix", "sec": "linalg" },
  "parallel_vec": { "latex": "{v1} \\parallel {v2}", "type": "infix", "sec": "linalg" },
  "perp_vec": { "latex": "{v1} \\perp {v2}", "type": "infix", "sec": "linalg" },
  "det": { "latex": "\\det({v1})", "type": "prefix", "sec": "linalg" },
  "trace": { "latex": "\\operatorname{{Tr}}({v1})", "type": "prefix", "sec": "linalg" },
  "transpose": { "latex": "{v1}^T", "type": "suffix", "sec": "linalg" },
  "hermitian": { "latex": "{v1}^\\dagger", "type": "suffix", "sec": "linalg" },
  "conjugate": { "latex": "{v1}^*", "type": "suffix", "sec": "linalg" },
  "inverse": { "latex": "{v1}^{{-1}}", "type": "suffix", "sec": "linalg" },
  "rank": { "latex": "\\operatorname{{rank}}({v1})", "type": "prefix", "sec": "linalg" },
  "norm": { "latex": "\\|{v1}\\|", "type": "prefix", "sec": "linalg" },
  "inner_prod": { "latex": "\\langle {v1}, {v2} \\rangle", "type": "functional", "sec": "linalg" },

  "neg": { "latex": "\\neg {v1}", "type": "prefix", "sec": "logic" },
  "land": { "latex": "{v1} \\land {v2}", "type": "infix", "sec": "logic" },
  "lor": { "latex": "{v1} \\lor {v2}", "type": "infix", "sec": "logic" },
  "xor": { "latex": "{v1} \\veebar {v2}", "type": "infix", "sec": "logic" },
  "implies": { "latex": "{v1} \\implies {v2}", "type": "infix", "sec": "logic" },
  "impliedby": { "latex": "{v1} \\impliedby {v2}", "type": "infix", "sec": "logic" },
  "iff": { "latex": "{v1} \\iff {v2}", "type": "infix", "sec": "logic" },
  "forall": { "latex": "\\forall {v1}", "type": "prefix", "sec": "logic" },
  "exists": { "latex": "\\exists {v1}", "type": "prefix", "sec": "logic" },
  "exists_unique": { "latex": "\\exists! {v1}", "type": "prefix", "sec": "logic" },
  "therefore": { "latex": "\\therefore {v1}", "type": "prefix", "sec": "logic" },
  "because": { "latex": "\\because {v1}", "type": "prefix", "sec": "logic" },
  "entails_syn": { "latex": "{v1} \\vdash {v2}", "type": "infix", "sec": "logic" },
  "entails_sem": { "latex": "{v1} \\vDash {v2}", "type": "infix", "sec": "logic" },

  "cong": { "latex": "{v1} \\cong {v2}", "type": "infix", "sec": "geometry" },
  "sim_geo": { "latex": "{v1} \\sim {v2}", "type": "infix", "sec": "geometry" },
  "angle": { "latex": "\\angle {v1}", "type": "prefix", "sec": "geometry" },
  "angle_meas": { "latex": "\\measuredangle {v1}", "type": "prefix", "sec": "geometry" },
  "angle_sph": { "latex": "\\sphericalangle {v1}", "type": "prefix", "sec": "geometry" },
  "sin": { "latex": "\\sin({v1})", "type": "prefix", "sec": "geometry" },
  "cos": { "latex": "\\cos({v1})", "type": "prefix", "sec": "geometry" },
  "tan": { "latex": "\\tan({v1})", "type": "prefix", "sec": "geometry" },
  "asin": { "latex": "\\arcsin({v1})", "type": "prefix", "sec": "geometry" },
  "acos": { "latex": "\\arccos({v1})", "type": "prefix", "sec": "geometry" },
  "deg": { "latex": "{v1}^\\circ", "type": "suffix", "sec": "geometry" },

  "partial": { "latex": "\\partial {v1}", "type": "prefix", "sec": "topology" },
  "closure": { "latex": "\\bar{{{v1}}}", "type": "prefix", "sec": "topology" },
  "interior": { "latex": "{v1}^\\circ", "type": "suffix", "sec": "topology" },
  "complement": { "latex": "{v1}^c", "type": "suffix", "sec": "topology" },
  "homeo": { "latex": "{v1} \\cong {v2}", "type": "infix", "sec": "topology" },
  "homotopy": { "latex": "{v1} \\approx {v2}", "type": "infix", "sec": "topology" },
  "fund_group": { "latex": "\\pi_{{n}}({v1})", "type": "prefix", "sec": "topology" },
  "homology": { "latex": "H_{{n}}({v1})", "type": "prefix", "sec": "topology" },
  "borel": { "latex": "\\mathcal{{B}}({v1})", "type": "prefix", "sec": "topology" },

  "rtimes": { "latex": "{v1} \\rtimes {v2}", "type": "infix", "sec": "abstract_algebra" },
  "iso_alg": { "latex": "{v1} \\cong {v2}", "type": "infix", "sec": "abstract_algebra" },
  "homo_alg": { "latex": "{v1} \\approx {v2}", "type": "infix", "sec": "abstract_algebra" },
  "normal_sub": { "latex": "{v1} \\trianglelefteq {v2}", "type": "infix", "sec": "abstract_algebra" },
  "ker": { "latex": "\\ker({v1})", "type": "prefix", "sec": "abstract_algebra" },
  "image": { "latex": "\\operatorname{{Im}}({v1})", "type": "prefix", "sec": "abstract_algebra" },
  "aut": { "latex": "\\operatorname{{Aut}}({v1})", "type": "prefix", "sec": "abstract_algebra" },
  "quotient_alg": { "latex": "{v1}/{v2}", "type": "infix", "sec": "abstract_algebra" },
  "commutator": { "latex": "[{v1}, {v2}]", "type": "functional", "sec": "abstract_algebra" },

  "arrow": { "latex": "{v1} \\to {v2}", "type": "infix", "sec": "category_theory" },
  "mono": { "latex": "{v1} \\hookrightarrow {v2}", "type": "infix", "sec": "category_theory" },
  "epi": { "latex": "{v1} \\twoheadrightarrow {v2}", "type": "infix", "sec": "category_theory" },
  "functor": { "latex": "{v1}: {v2} \\to {v3}", "type": "functional", "sec": "category_theory" },
  "nat_trans": { "latex": "{v1}: {v2} \\Rightarrow {v3}", "type": "functional", "sec": "category_theory" },
  "adjunction": { "latex": "{v1} \\dashv {v2}", "type": "infix", "sec": "category_theory" },
  "colim": { "latex": "\\operatorname{{colim}} {v1}", "type": "prefix", "sec": "category_theory" },
  "hom_set": { "latex": "\\operatorname{{Hom}}({v1}, {v2})", "type": "functional", "sec": "category_theory" },

  "covariant": { "latex": "\\nabla_{{{v2}}} {v1}", "type": "functional", "sec": "tensors" },
  "partial_tensor": { "latex": "{v1}_{{,{v2}}}", "type": "functional", "sec": "tensors" },
  "lie_deriv": { "latex": "\\mathcal{{L}}_{{{v1}}} {v2}", "type": "functional", "sec": "tensors" },
  "exterior_deriv": { "latex": "d{v1}", "type": "prefix", "sec": "tensors" },
  "christoffel": { "latex": "\\Gamma^{{{v1}}}_{{{v2}{v3}}}", "type": "functional", "sec": "tensors" },
  "riemann": { "latex": "R^{{{v1}}}_{{{v2}{v3}{v4}}}", "type": "functional", "sec": "tensors" },
  "kronecker": { "latex": "\\delta^{{{v1}}}_{{{v2}}}", "type": "functional", "sec": "tensors" },
  "levicivita": { "latex": "\\epsilon_{{{v1}{v2}{v3}}}", "type": "functional", "sec": "tensors" },

  "prob_measure": { "latex": "P({v1})", "type": "prefix", "sec": "probability" },
  "prob_cond": { "latex": "P({v1}|{v2})", "type": "functional", "sec": "probability" },
  "expectation": { "latex": "E[{v1}]", "type": "prefix", "sec": "probability" },
  "variance": { "latex": "\\operatorname{{Var}}({v1})", "type": "prefix", "sec": "probability" },
  "covariance": { "latex": "\\operatorname{{Cov}}({v1}, {v2})", "type": "functional", "sec": "probability" },
  "std_dev": { "latex": "\\sigma", "type": "prefix", "sec": "probability" },
  "dist_sim": { "latex": "{v1} \\sim {v2}", "type": "infix", "sec": "probability" },
  "sample_mean": { "latex": "\\bar{{{v1}}}", "type": "prefix", "sec": "probability" },
  "param_estimate": { "latex": "\\hat{{{v1}}}", "type": "prefix", "sec": "probability" },
  "cdf_phi": { "latex": "\\Phi({v1})", "type": "prefix", "sec": "probability" },

  "bra": { "latex": "\\langle {v1} |", "type": "prefix", "sec": "quantum" },
  "ket": { "latex": "| {v1} \\rangle", "type": "prefix", "sec": "quantum" },
  "bracket": { "latex": "\\langle {v1} | {v2} \\rangle", "type": "functional", "sec": "quantum" },
  "adjoint": { "latex": "{v1}^\\dagger", "type": "suffix", "sec": "quantum" },
  "operator_hat": { "latex": "\\hat{{{v1}}}", "type": "prefix", "sec": "quantum" },
  "commutator_hat": { "latex": "[{v1}, {v2}]", "type": "functional", "sec": "quantum" },
  "anticommutator": { "latex": "\\{{{v1}, {v2}\\}}", "type": "functional", "sec": "quantum" },
  "exp_val_quantum": { "latex": "\\langle {v1} \\rangle", "type": "prefix", "sec": "quantum" },
  "hbar": { "latex": "\\hbar", "type": "prefix", "sec": "quantum" },
  "complex_conj": { "latex": "{v1}^*", "type": "suffix", "sec": "quantum" }
}
